{"_ts":[1540836773],"_r":{"breakdown":{"html":{"bytes":[4248],"requests":[2]},"js":{"bytes":[2662265],"requests":[6]},"css":{"bytes":[0],"requests":[0]},"image":{"bytes":[1987999],"requests":[8]},"flash":{"bytes":[0],"requests":[0]},"font":{"bytes":[237344],"requests":[4]},"video":{"bytes":[0],"requests":[0]},"other":{"bytes":[11854],"requests":[21]}},"date":[1540836773],"domElements":[97],"domInteractive":[7681.3333333333],"firstPaint":[927.96666666497],"fullyLoaded":[15162.333333333],"id":["181029_G0_d950575c12d7d188c7681868da23a060"],"loadTime":[7959.3333333333],"render":[10133.333333333],"SpeedIndex":[10300.333333333],"TTFB":[858],"videoFrames":[[{"_i":"ms_000000.jpg","_t":0,"_vc":0},{"_i":"ms_009800.jpg","_t":9800,"_vc":92},{"_i":"ms_010000.jpg","_t":10000,"_vc":93},{"_i":"ms_010100.jpg","_t":10100,"_vc":93},{"_i":"ms_010200.jpg","_t":10200,"_vc":95},{"_i":"ms_010300.jpg","_t":10300,"_vc":95},{"_i":"ms_010400.jpg","_t":10400,"_vc":95},{"_i":"ms_010500.jpg","_t":10500,"_vc":97},{"_i":"ms_010600.jpg","_t":10600,"_vc":96},{"_i":"ms_010700.jpg","_t":10700,"_vc":97},{"_i":"ms_011200.jpg","_t":11200,"_vc":97},{"_i":"ms_011800.jpg","_t":11800,"_vc":97},{"_i":"ms_012300.jpg","_t":12300,"_vc":97},{"_i":"ms_012700.jpg","_t":12700,"_vc":97},{"_i":"ms_013100.jpg","_t":13100,"_vc":97},{"_i":"ms_013300.jpg","_t":13300,"_vc":97},{"_i":"ms_013700.jpg","_t":13700,"_vc":97},{"_i":"ms_013800.jpg","_t":13800,"_vc":97},{"_i":"ms_014100.jpg","_t":14100,"_vc":97},{"_i":"ms_014300.jpg","_t":14300,"_vc":99},{"_i":"ms_014400.jpg","_t":14400,"_vc":100}]],"visualComplete":[14466.666666667],"lighthouse":[27],"pagespeed":[95]}}