{"_ts":[1593591657,1593636801,1593680328],"_r":{"breakdown":{"html":{"bytes":[41538,41512,41270],"requests":[3,3,3]},"js":{"bytes":[222032,755764,758406],"requests":[4,21,21]},"css":{"bytes":[0,0,0],"requests":[0,0,0]},"image":{"bytes":[603027,603951,604120],"requests":[8,10,10]},"flash":{"bytes":[0,0,0],"requests":[0,0,0]},"font":{"bytes":[0,304140,304140],"requests":[0,6,6]},"video":{"bytes":[0,0,0],"requests":[0,0,0]},"other":{"bytes":[2194,16359,16249],"requests":[2,29,29]}},"date":[1593591657,1593636801,1593680328],"domElements":[2155.3333333333335,2223,1508.6666666666667],"domInteractive":[2072.6666666666665,2177.6666666666665,1975.3333333333333],"firstPaint":[1572.3999999997332,1890.1333333342334,1591.6333333346665],"fullyLoaded":[13121,15419.666666666666,11684.666666666666],"id":["200701_5S_5d463bd1e710e3974390d401b059014c","200701_1R_bf9d5371c548f1a2fc46eeab686260b2","200702_SJ_8fa834b5dd494ff64809491c0462bbca"],"loadTime":[11538.333333333334,14457.333333333334,10880],"render":[5016.333333333333,5269,4464.333333333333],"SpeedIndex":[7291.333333333333,8839.333333333334,6678],"TTFB":[1253.3333333333333,1547,1255.6666666666667],"videoFrames":[[{"_i":"ms_000000.jpg","_t":0,"_vc":0},{"_i":"ms_004668.jpg","_t":4668,"_vc":100}],[{"_i":"ms_000000.jpg","_t":0,"_vc":0},{"_i":"ms_004145.jpg","_t":4145,"_vc":51},{"_i":"ms_004159.jpg","_t":4159,"_vc":51},{"_i":"ms_004178.jpg","_t":4178,"_vc":51},{"_i":"ms_004195.jpg","_t":4195,"_vc":51},{"_i":"ms_004544.jpg","_t":4544,"_vc":51},{"_i":"ms_004561.jpg","_t":4561,"_vc":51},{"_i":"ms_004576.jpg","_t":4576,"_vc":51},{"_i":"ms_004601.jpg","_t":4601,"_vc":51},{"_i":"ms_004628.jpg","_t":4628,"_vc":51},{"_i":"ms_004709.jpg","_t":4709,"_vc":51},{"_i":"ms_004814.jpg","_t":4814,"_vc":51},{"_i":"ms_004910.jpg","_t":4910,"_vc":51},{"_i":"ms_005455.jpg","_t":5455,"_vc":51},{"_i":"ms_006301.jpg","_t":6301,"_vc":51},{"_i":"ms_007080.jpg","_t":7080,"_vc":51},{"_i":"ms_007129.jpg","_t":7129,"_vc":51},{"_i":"ms_007212.jpg","_t":7212,"_vc":51},{"_i":"ms_008423.jpg","_t":8423,"_vc":51},{"_i":"ms_008539.jpg","_t":8539,"_vc":51},{"_i":"ms_009351.jpg","_t":9351,"_vc":51},{"_i":"ms_009601.jpg","_t":9601,"_vc":51},{"_i":"ms_010630.jpg","_t":10630,"_vc":51},{"_i":"ms_010716.jpg","_t":10716,"_vc":51},{"_i":"ms_010803.jpg","_t":10803,"_vc":51},{"_i":"ms_012289.jpg","_t":12289,"_vc":92},{"_i":"ms_012371.jpg","_t":12371,"_vc":93},{"_i":"ms_012643.jpg","_t":12643,"_vc":95},{"_i":"ms_013466.jpg","_t":13466,"_vc":91},{"_i":"ms_013614.jpg","_t":13614,"_vc":91},{"_i":"ms_013962.jpg","_t":13962,"_vc":99},{"_i":"ms_014161.jpg","_t":14161,"_vc":99},{"_i":"ms_014214.jpg","_t":14214,"_vc":99},{"_i":"ms_014361.jpg","_t":14361,"_vc":99},{"_i":"ms_014494.jpg","_t":14494,"_vc":99},{"_i":"ms_014511.jpg","_t":14511,"_vc":99},{"_i":"ms_014632.jpg","_t":14632,"_vc":98},{"_i":"ms_014742.jpg","_t":14742,"_vc":100}],[{"_i":"ms_000000.jpg","_t":0,"_vc":0},{"_i":"ms_004842.jpg","_t":4842,"_vc":51},{"_i":"ms_005070.jpg","_t":5070,"_vc":51},{"_i":"ms_005091.jpg","_t":5091,"_vc":51},{"_i":"ms_005121.jpg","_t":5121,"_vc":51},{"_i":"ms_005137.jpg","_t":5137,"_vc":51},{"_i":"ms_005171.jpg","_t":5171,"_vc":51},{"_i":"ms_005193.jpg","_t":5193,"_vc":51},{"_i":"ms_005205.jpg","_t":5205,"_vc":51},{"_i":"ms_005223.jpg","_t":5223,"_vc":51},{"_i":"ms_005452.jpg","_t":5452,"_vc":51},{"_i":"ms_006199.jpg","_t":6199,"_vc":51},{"_i":"ms_006414.jpg","_t":6414,"_vc":51},{"_i":"ms_006599.jpg","_t":6599,"_vc":51},{"_i":"ms_006617.jpg","_t":6617,"_vc":51},{"_i":"ms_006714.jpg","_t":6714,"_vc":51},{"_i":"ms_006801.jpg","_t":6801,"_vc":51},{"_i":"ms_006901.jpg","_t":6901,"_vc":51},{"_i":"ms_007397.jpg","_t":7397,"_vc":51},{"_i":"ms_007409.jpg","_t":7409,"_vc":51},{"_i":"ms_007512.jpg","_t":7512,"_vc":51},{"_i":"ms_007609.jpg","_t":7609,"_vc":51},{"_i":"ms_007714.jpg","_t":7714,"_vc":51},{"_i":"ms_008023.jpg","_t":8023,"_vc":51},{"_i":"ms_008109.jpg","_t":8109,"_vc":51},{"_i":"ms_008201.jpg","_t":8201,"_vc":51},{"_i":"ms_008310.jpg","_t":8310,"_vc":51},{"_i":"ms_008719.jpg","_t":8719,"_vc":51},{"_i":"ms_008805.jpg","_t":8805,"_vc":51},{"_i":"ms_008905.jpg","_t":8905,"_vc":51},{"_i":"ms_009004.jpg","_t":9004,"_vc":51},{"_i":"ms_009558.jpg","_t":9558,"_vc":51},{"_i":"ms_009633.jpg","_t":9633,"_vc":51},{"_i":"ms_010312.jpg","_t":10312,"_vc":51},{"_i":"ms_010415.jpg","_t":10415,"_vc":51},{"_i":"ms_010610.jpg","_t":10610,"_vc":51},{"_i":"ms_012088.jpg","_t":12088,"_vc":93},{"_i":"ms_012170.jpg","_t":12170,"_vc":95},{"_i":"ms_012455.jpg","_t":12455,"_vc":96},{"_i":"ms_013604.jpg","_t":13604,"_vc":91},{"_i":"ms_014110.jpg","_t":14110,"_vc":99},{"_i":"ms_014292.jpg","_t":14292,"_vc":99},{"_i":"ms_014311.jpg","_t":14311,"_vc":98},{"_i":"ms_014402.jpg","_t":14402,"_vc":95},{"_i":"ms_014520.jpg","_t":14520,"_vc":96},{"_i":"ms_014575.jpg","_t":14575,"_vc":100}]],"visualComplete":[11362.333333333334,14793.333333333334,10157.666666666666],"lighthouse":[32,32,32],"pagespeed":[null,null,null]}}