{"_ts":[1564709561,1564796879],"_r":{"breakdown":{"html":{"bytes":[24868,25666],"requests":[4,6]},"js":{"bytes":[39389,1881745],"requests":[2,40]},"css":{"bytes":[0,0],"requests":[0,0]},"image":{"bytes":[68448,163262],"requests":[5,12]},"flash":{"bytes":[0,0],"requests":[0,0]},"font":{"bytes":[0,341004],"requests":[0,7]},"video":{"bytes":[0,0],"requests":[0,0]},"other":{"bytes":[23,14140],"requests":[1,27]}},"date":[1564709561,1564796879],"domElements":[1424,1698],"domInteractive":[2291,2289],"firstPaint":[2499.5999999956,2161.399999999],"fullyLoaded":[5639,15677],"id":["190802_Y5_16efbc9a03880e0081d8959655a8ec67","190803_RV_20c050641605b254e2c8441c202c9909"],"loadTime":[3132,12221],"render":[2816,2661],"SpeedIndex":[2816,7370],"TTFB":[1975,1855],"videoFrames":[[{"_i":"ms_000000.jpg","_t":0,"_vc":0},{"_i":"ms_002816.jpg","_t":2816,"_vc":100}],[{"_i":"ms_000000.jpg","_t":0,"_vc":0},{"_i":"ms_002661.jpg","_t":2661,"_vc":39},{"_i":"ms_002678.jpg","_t":2678,"_vc":39},{"_i":"ms_002693.jpg","_t":2693,"_vc":40},{"_i":"ms_002715.jpg","_t":2715,"_vc":40},{"_i":"ms_002778.jpg","_t":2778,"_vc":40},{"_i":"ms_003053.jpg","_t":3053,"_vc":40},{"_i":"ms_003115.jpg","_t":3115,"_vc":40},{"_i":"ms_003981.jpg","_t":3981,"_vc":40},{"_i":"ms_003996.jpg","_t":3996,"_vc":40},{"_i":"ms_004030.jpg","_t":4030,"_vc":40},{"_i":"ms_004046.jpg","_t":4046,"_vc":40},{"_i":"ms_004066.jpg","_t":4066,"_vc":40},{"_i":"ms_004089.jpg","_t":4089,"_vc":40},{"_i":"ms_004116.jpg","_t":4116,"_vc":40},{"_i":"ms_004146.jpg","_t":4146,"_vc":40},{"_i":"ms_005812.jpg","_t":5812,"_vc":40},{"_i":"ms_006811.jpg","_t":6811,"_vc":40},{"_i":"ms_006848.jpg","_t":6848,"_vc":40},{"_i":"ms_008178.jpg","_t":8178,"_vc":40},{"_i":"ms_008378.jpg","_t":8378,"_vc":40},{"_i":"ms_009028.jpg","_t":9028,"_vc":40},{"_i":"ms_009111.jpg","_t":9111,"_vc":40},{"_i":"ms_009129.jpg","_t":9129,"_vc":40},{"_i":"ms_010178.jpg","_t":10178,"_vc":81},{"_i":"ms_010345.jpg","_t":10345,"_vc":84},{"_i":"ms_010979.jpg","_t":10979,"_vc":88},{"_i":"ms_011044.jpg","_t":11044,"_vc":89},{"_i":"ms_011294.jpg","_t":11294,"_vc":90},{"_i":"ms_011345.jpg","_t":11345,"_vc":93},{"_i":"ms_011361.jpg","_t":11361,"_vc":95},{"_i":"ms_011412.jpg","_t":11412,"_vc":94},{"_i":"ms_011428.jpg","_t":11428,"_vc":91},{"_i":"ms_011494.jpg","_t":11494,"_vc":99},{"_i":"ms_011795.jpg","_t":11795,"_vc":100},{"_i":"ms_011914.jpg","_t":11914,"_vc":99},{"_i":"ms_011929.jpg","_t":11929,"_vc":99},{"_i":"ms_011949.jpg","_t":11949,"_vc":96},{"_i":"ms_011968.jpg","_t":11968,"_vc":95},{"_i":"ms_011993.jpg","_t":11993,"_vc":95},{"_i":"ms_012011.jpg","_t":12011,"_vc":94},{"_i":"ms_012055.jpg","_t":12055,"_vc":94},{"_i":"ms_012145.jpg","_t":12145,"_vc":97},{"_i":"ms_012162.jpg","_t":12162,"_vc":100}]],"visualComplete":[2816,11795],"lighthouse":[59,33],"pagespeed":[81,82]}}