{"_ts":[1588296089],"_r":{"breakdown":{"html":{"bytes":[33989],"requests":[3]},"js":{"bytes":[596075],"requests":[20]},"css":{"bytes":[0],"requests":[0]},"image":{"bytes":[503516],"requests":[8]},"flash":{"bytes":[0],"requests":[0]},"font":{"bytes":[304140],"requests":[6]},"video":{"bytes":[0],"requests":[0]},"other":{"bytes":[15892],"requests":[28]}},"date":[1588296089],"domElements":[2085],"domInteractive":[3110.3333333333335],"firstPaint":[2842.733333333533],"fullyLoaded":[20021.666666666668],"id":["200501_R4_47d537d2c9b70c37d04b2bfc4c56b5f7"],"loadTime":[16127],"render":[5854],"SpeedIndex":[9411.333333333334],"TTFB":[2442],"videoFrames":[[{"_i":"ms_000000.jpg","_t":0,"_vc":0},{"_i":"ms_005506.jpg","_t":5506,"_vc":51},{"_i":"ms_005622.jpg","_t":5622,"_vc":51},{"_i":"ms_005642.jpg","_t":5642,"_vc":51},{"_i":"ms_005660.jpg","_t":5660,"_vc":51},{"_i":"ms_005692.jpg","_t":5692,"_vc":51},{"_i":"ms_005706.jpg","_t":5706,"_vc":51},{"_i":"ms_005722.jpg","_t":5722,"_vc":51},{"_i":"ms_005741.jpg","_t":5741,"_vc":51},{"_i":"ms_005756.jpg","_t":5756,"_vc":51},{"_i":"ms_005804.jpg","_t":5804,"_vc":51},{"_i":"ms_005906.jpg","_t":5906,"_vc":51},{"_i":"ms_006003.jpg","_t":6003,"_vc":51},{"_i":"ms_006404.jpg","_t":6404,"_vc":51},{"_i":"ms_006505.jpg","_t":6505,"_vc":51},{"_i":"ms_007349.jpg","_t":7349,"_vc":51},{"_i":"ms_007461.jpg","_t":7461,"_vc":51},{"_i":"ms_008390.jpg","_t":8390,"_vc":51},{"_i":"ms_008456.jpg","_t":8456,"_vc":51},{"_i":"ms_008656.jpg","_t":8656,"_vc":51},{"_i":"ms_008708.jpg","_t":8708,"_vc":51},{"_i":"ms_008822.jpg","_t":8822,"_vc":51},{"_i":"ms_008921.jpg","_t":8921,"_vc":51},{"_i":"ms_009009.jpg","_t":9009,"_vc":51},{"_i":"ms_010348.jpg","_t":10348,"_vc":51},{"_i":"ms_010799.jpg","_t":10799,"_vc":51},{"_i":"ms_011013.jpg","_t":11013,"_vc":51},{"_i":"ms_011646.jpg","_t":11646,"_vc":51},{"_i":"ms_012322.jpg","_t":12322,"_vc":51},{"_i":"ms_012507.jpg","_t":12507,"_vc":51},{"_i":"ms_014248.jpg","_t":14248,"_vc":51},{"_i":"ms_014515.jpg","_t":14515,"_vc":51},{"_i":"ms_016257.jpg","_t":16257,"_vc":94},{"_i":"ms_017651.jpg","_t":17651,"_vc":96},{"_i":"ms_018293.jpg","_t":18293,"_vc":91},{"_i":"ms_019272.jpg","_t":19272,"_vc":99},{"_i":"ms_019974.jpg","_t":19974,"_vc":99},{"_i":"ms_020008.jpg","_t":20008,"_vc":96},{"_i":"ms_020187.jpg","_t":20187,"_vc":100}]],"visualComplete":[15496.666666666666],"lighthouse":[33],"pagespeed":[null]}}