{"_ts":[1598927918],"_r":{"breakdown":{"html":{"bytes":[46721],"requests":[3]},"js":{"bytes":[766648],"requests":[23]},"css":{"bytes":[0],"requests":[0]},"image":{"bytes":[705067],"requests":[10]},"flash":{"bytes":[0],"requests":[0]},"font":{"bytes":[304140],"requests":[6]},"video":{"bytes":[0],"requests":[0]},"other":{"bytes":[273506],"requests":[31]}},"date":[1598927918],"domElements":[1528],"domInteractive":[2181.3333333333335],"firstPaint":[1884.0999999993],"fullyLoaded":[18096],"id":["200901_MT_49d70f4cb6d1724e31d8cc294c07e2eb"],"loadTime":[15939.666666666666],"render":[4098.666666666667],"SpeedIndex":[8294.333333333334],"TTFB":[1631.3333333333333],"videoFrames":[[{"_i":"ms_000000.jpg","_t":0,"_vc":0},{"_i":"ms_006723.jpg","_t":6723,"_vc":51},{"_i":"ms_007113.jpg","_t":7113,"_vc":51},{"_i":"ms_007138.jpg","_t":7138,"_vc":51},{"_i":"ms_007170.jpg","_t":7170,"_vc":51},{"_i":"ms_007190.jpg","_t":7190,"_vc":51},{"_i":"ms_007202.jpg","_t":7202,"_vc":51},{"_i":"ms_007223.jpg","_t":7223,"_vc":51},{"_i":"ms_007245.jpg","_t":7245,"_vc":51},{"_i":"ms_007257.jpg","_t":7257,"_vc":51},{"_i":"ms_007312.jpg","_t":7312,"_vc":51},{"_i":"ms_007405.jpg","_t":7405,"_vc":51},{"_i":"ms_007885.jpg","_t":7885,"_vc":51},{"_i":"ms_007917.jpg","_t":7917,"_vc":51},{"_i":"ms_008007.jpg","_t":8007,"_vc":51},{"_i":"ms_008115.jpg","_t":8115,"_vc":51},{"_i":"ms_008220.jpg","_t":8220,"_vc":51},{"_i":"ms_008380.jpg","_t":8380,"_vc":51},{"_i":"ms_008600.jpg","_t":8600,"_vc":51},{"_i":"ms_008720.jpg","_t":8720,"_vc":51},{"_i":"ms_008806.jpg","_t":8806,"_vc":51},{"_i":"ms_008903.jpg","_t":8903,"_vc":51},{"_i":"ms_009004.jpg","_t":9004,"_vc":51},{"_i":"ms_009293.jpg","_t":9293,"_vc":51},{"_i":"ms_009310.jpg","_t":9310,"_vc":51},{"_i":"ms_009429.jpg","_t":9429,"_vc":51},{"_i":"ms_010354.jpg","_t":10354,"_vc":51},{"_i":"ms_010519.jpg","_t":10519,"_vc":51},{"_i":"ms_011201.jpg","_t":11201,"_vc":51},{"_i":"ms_011315.jpg","_t":11315,"_vc":51},{"_i":"ms_011485.jpg","_t":11485,"_vc":51},{"_i":"ms_011517.jpg","_t":11517,"_vc":51},{"_i":"ms_011600.jpg","_t":11600,"_vc":51},{"_i":"ms_011722.jpg","_t":11722,"_vc":51},{"_i":"ms_012282.jpg","_t":12282,"_vc":51},{"_i":"ms_012527.jpg","_t":12527,"_vc":51},{"_i":"ms_013010.jpg","_t":13010,"_vc":51},{"_i":"ms_013674.jpg","_t":13674,"_vc":51},{"_i":"ms_014024.jpg","_t":14024,"_vc":51},{"_i":"ms_014504.jpg","_t":14504,"_vc":51},{"_i":"ms_015086.jpg","_t":15086,"_vc":51},{"_i":"ms_016077.jpg","_t":16077,"_vc":51},{"_i":"ms_017586.jpg","_t":17586,"_vc":51},{"_i":"ms_018087.jpg","_t":18087,"_vc":51},{"_i":"ms_019877.jpg","_t":19877,"_vc":93},{"_i":"ms_020024.jpg","_t":20024,"_vc":95},{"_i":"ms_021253.jpg","_t":21253,"_vc":90},{"_i":"ms_022944.jpg","_t":22944,"_vc":94},{"_i":"ms_023528.jpg","_t":23528,"_vc":99},{"_i":"ms_023823.jpg","_t":23823,"_vc":100}]],"visualComplete":[14662.666666666666],"lighthouse":[null],"pagespeed":[null]}}