{"_ts":[1575562651],"_r":{"breakdown":{"html":{"bytes":[0],"requests":[0]},"js":{"bytes":[0],"requests":[0]},"css":{"bytes":[0],"requests":[0]},"image":{"bytes":[0],"requests":[0]},"flash":{"bytes":[0],"requests":[0]},"font":{"bytes":[0],"requests":[0]},"video":{"bytes":[0],"requests":[0]},"other":{"bytes":[0],"requests":[1]}},"date":[1575562651],"domElements":[null],"domInteractive":[0],"firstPaint":[0],"fullyLoaded":[0],"id":["191205_PC_52c522cd3d65e8585a0f0c483141070b"],"loadTime":[0],"render":[1492],"SpeedIndex":[1492],"TTFB":[0],"videoFrames":[[{"_i":"ms_000000.jpg","_t":0,"_vc":0},{"_i":"ms_001492.jpg","_t":1492,"_vc":100}]],"visualComplete":[1492],"lighthouse":[null],"pagespeed":[67]}}